<?xml version="1.0" encoding="UTF-8"?>

<ValueSet xmlns="http://hl7.org/fhir">
  <id value="qicore-observation-verification"/>
  <meta>
    <profile value="http://hl7.org/fhir/StructureDefinition/valueset-shareable-definition"/>
  </meta>
  <url value="http://hl7.org/fhir/qicore/ValueSet/qicore-observation-verification"/>
  <name value="QICore Observation Verification Method"/>
  <status value="draft"/>
  <publisher value="HL7 Clinical Quality Information (CQI) Work Group"/>
  <contact>
    <telecom>
      <system value="other"/>
      <value value="http://www.hl7.org/Special/committees/cqi"/>
    </telecom>
  </contact>
  <description value="Code for method by which the observation result was validated, e.g., human review, sliding average."/>
  <compose>
    <include>
      <system value="http://hl7.org/fhir/qicore-observation-verification-method"/>
    </include>
  </compose>
</ValueSet>