<StructureDefinition xmlns="http://hl7.org/fhir">
   <id value="SortCriteria"/>
   <url value="{http://www.omg.org/spec/CTS2/1.1/Core}SortCriteria"/>
   <name value="SortCriteria"/>
   <display value="CTS2.SortCriteria"/>
   <status value="draft"/>
   <publisher value="Generated by Xsd-to-FHIR"/>
   <contact>
      <name value="Visit the Github repository for more information"/>
      <telecom>
         <system value="other"/>
         <value value="https://github.com/cts2/CTS2-to-FHIR"/>
      </telecom>
   </contact>
   <date value="2016-02-08T19:11:02-07:00"/>
   <description value="An ordered list of sort criterion. The first entry in the list identifies the primary sort order, the second entry the sub sort order, etc. "/>
   <fhirVersion value="1.4.0"/>
   <kind value="logical"/>
   <abstract value="false"/>
   <snapshot>
      <element>
         <path value="SortCriteria"/>
         <short value="SortCriteria"/>
         <definition value="An ordered list of sort criterion. The first entry in the list identifies the primary sort order, the second entry the sub sort order, etc. "/>
         <min value="0"/>
         <max value="*"/>
      </element>
      <element>
         <path value="SortCriteria.entry"/>
         <name value="entry"/>
         <short value="TODO: Description"/>
         <definition value="TODO: Description"/>
         <min value="0"/>
         <max value="*"/>
         <type>
            <code value="SortCriterion"/>
         </type>
      </element>
   </snapshot>
</StructureDefinition>