<?xml version="1.0" encoding="UTF-8"?>

<ValueSet xmlns="http://hl7.org/fhir">
  <id value="filter-operator"/>
  <meta>
    <lastUpdated value="2020-12-28T16:55:11.085+11:00"/>
    <profile value="http://hl7.org/fhir/StructureDefinition/shareablevalueset"/>
  </meta>
  <text>
    <status value="generated"/>
    <div xmlns="http://www.w3.org/1999/xhtml">
      <ul>
        <li>Include all codes defined in 
          <a href="codesystem-filter-operator.html">
            <code>http://hl7.org/fhir/filter-operator</code>
          </a>
        </li>
      </ul>
    </div>
  </text>
  <extension url="http://hl7.org/fhir/StructureDefinition/structuredefinition-wg">
    <valueCode value="vocab"/>
  </extension>
  <extension url="http://hl7.org/fhir/StructureDefinition/structuredefinition-standards-status">
    <valueCode value="normative"/>
  </extension>
  <extension url="http://hl7.org/fhir/StructureDefinition/structuredefinition-normative-version">
    <valueCode value="4.0.0"/>
  </extension>
  <extension url="http://hl7.org/fhir/StructureDefinition/structuredefinition-fmm">
    <valueInteger value="5"/>
  </extension>
  <url value="http://hl7.org/fhir/ValueSet/filter-operator"/>
  <identifier>
    <system value="urn:ietf:rfc:3986"/>
    <value value="urn:oid:2.16.840.1.113883.4.642.3.478"/>
  </identifier>
  <version value="4.6.0"/>
  <name value="FilterOperator"/>
  <title value="FilterOperator"/>
  <status value="active"/>
  <experimental value="false"/>
  <date value="2020-12-28T16:55:11+11:00"/>
  <publisher value="HL7 (FHIR Project)"/>
  <contact>
    <telecom>
      <system value="url"/>
      <value value="http://hl7.org/fhir"/>
    </telecom>
    <telecom>
      <system value="email"/>
      <value value="fhir@lists.hl7.org"/>
    </telecom>
  </contact>
  <description value="The kind of operation to perform as a part of a property based filter."/>
  <immutable value="true"/>
  <compose>
    <include>
      <system value="http://hl7.org/fhir/filter-operator"/>
    </include>
  </compose>
</ValueSet>