{"resourceType":"ValueSet","id":"abstract-types","meta":{"lastUpdated":"2016-12-13T08:52:49.682+11:00","profile":["http://hl7.org/fhir/StructureDefinition/valueset-shareable-definition"]},"text":{"status":"generated","div":"<div xmlns=\"http://www.w3.org/1999/xhtml\"><h2>AbstractType</h2><div><p>A type defined by FHIR that is an abstract type</p>\n</div><p>This value set includes codes from the following code systems:</p><ul><li>Include all codes defined in <a href=\"codesystem-abstract-types.html\">http://hl7.org/fhir/abstract-types</a></li></ul></div>"},"url":"http://hl7.org/fhir/ValueSet/abstract-types","identifier":[{"system":"urn:ietf:rfc:3986","value":"urn:oid:2.16.840.1.113883.4.642.2.abstract-types"}],"version":"1.9.0","name":"AbstractType","status":"draft","experimental":false,"publisher":"HL7 (FHIR Project)","contact":[{"telecom":[{"system":"url","value":"http://hl7.org/fhir"},{"system":"email","value":"fhir@lists.hl7.org"}]}],"date":"2016-12-13T08:52:49+11:00","description":"A type defined by FHIR that is an abstract type","immutable":true,"compose":{"include":[{"system":"http://hl7.org/fhir/abstract-types"}]},"expansion":{"identifier":"urn:uuid:2984281b-ba18-4db8-b5e8-d8fc21451fc9","timestamp":"2016-12-13T08:57:54+11:00","parameter":[{"name":"version","valueUri":"http://hl7.org/fhir/abstract-types|1.9.0"}],"contains":[{"system":"http://hl7.org/fhir/abstract-types","code":"Type","display":"Type"},{"system":"http://hl7.org/fhir/abstract-types","code":"Any","display":"Any"}]}}