{"resourceType":"ValueSet","id":"object-role","meta":{"lastUpdated":"2018-08-08T21:21:20.522+10:00","profile":["http://hl7.org/fhir/StructureDefinition/shareablevalueset"]},"text":{"status":"generated","div":"<div xmlns=\"http://www.w3.org/1999/xhtml\"><h2>AuditEventEntityRole</h2><div><p>Code representing the role the entity played in the audit event.</p>\n</div><p><b>Copyright Statement:</b> These codes are excerpted from Digital Imaging and Communications in Medicine (DICOM) Standard, Part 16: Content Mapping Resource, Copyright © 2011 by the National Electrical Manufacturers Association.</p><p>This value set includes codes from the following code systems:</p><ul><li>Include all codes defined in <a href=\"codesystem-object-role.html\"><code>http://terminology.hl7.org/CodeSystem/object-role</code></a></li></ul></div>"},"extension":[{"url":"http://hl7.org/fhir/StructureDefinition/structuredefinition-wg","valueCode":"sec"},{"url":"http://hl7.org/fhir/StructureDefinition/structuredefinition-standards-status","valueString":"Trial Use"},{"url":"http://hl7.org/fhir/StructureDefinition/structuredefinition-fmm","valueInteger":3}],"url":"http://hl7.org/fhir/ValueSet/object-role","identifier":[{"system":"urn:ietf:rfc:3986","value":"urn:oid:2.16.840.1.113883.4.642.3.460"}],"version":"3.4.0","name":"AuditEventEntityRole","status":"draft","experimental":false,"date":"2018-08-08T21:21:20+10:00","publisher":"HL7 (FHIR Project)","contact":[{"telecom":[{"system":"url","value":"http://hl7.org/fhir"},{"system":"email","value":"fhir@lists.hl7.org"}]}],"description":"Code representing the role the entity played in the audit event.","immutable":true,"copyright":"These codes are excerpted from Digital Imaging and Communications in Medicine (DICOM) Standard, Part 16: Content Mapping Resource, Copyright © 2011 by the National Electrical Manufacturers Association.","compose":{"include":[{"system":"http://terminology.hl7.org/CodeSystem/object-role"}]},"expansion":{"identifier":"urn:uuid:ca4bb87b-7b6a-4c07-a6c9-35d64103dc83","timestamp":"2018-08-08T21:37:49+10:00","total":24,"parameter":[{"name":"excludeNested","valueBoolean":true},{"name":"includeDesignations","valueBoolean":true},{"name":"version","valueUri":"http://terminology.hl7.org/CodeSystem/object-role|3.4.0"}],"contains":[{"system":"http://terminology.hl7.org/CodeSystem/object-role","code":"1","display":"Patient"},{"system":"http://terminology.hl7.org/CodeSystem/object-role","code":"2","display":"Location"},{"system":"http://terminology.hl7.org/CodeSystem/object-role","code":"3","display":"Report"},{"system":"http://terminology.hl7.org/CodeSystem/object-role","code":"4","display":"Domain Resource"},{"system":"http://terminology.hl7.org/CodeSystem/object-role","code":"5","display":"Master file"},{"system":"http://terminology.hl7.org/CodeSystem/object-role","code":"6","display":"User"},{"system":"http://terminology.hl7.org/CodeSystem/object-role","code":"7","display":"List"},{"system":"http://terminology.hl7.org/CodeSystem/object-role","code":"8","display":"Doctor"},{"system":"http://terminology.hl7.org/CodeSystem/object-role","code":"9","display":"Subscriber"},{"system":"http://terminology.hl7.org/CodeSystem/object-role","code":"10","display":"Guarantor"},{"system":"http://terminology.hl7.org/CodeSystem/object-role","code":"11","display":"Security User Entity"},{"system":"http://terminology.hl7.org/CodeSystem/object-role","code":"12","display":"Security User Group"},{"system":"http://terminology.hl7.org/CodeSystem/object-role","code":"13","display":"Security Resource"},{"system":"http://terminology.hl7.org/CodeSystem/object-role","code":"14","display":"Security Granularity Definition"},{"system":"http://terminology.hl7.org/CodeSystem/object-role","code":"15","display":"Practitioner"},{"system":"http://terminology.hl7.org/CodeSystem/object-role","code":"16","display":"Data Destination"},{"system":"http://terminology.hl7.org/CodeSystem/object-role","code":"17","display":"Data Repository"},{"system":"http://terminology.hl7.org/CodeSystem/object-role","code":"18","display":"Schedule"},{"system":"http://terminology.hl7.org/CodeSystem/object-role","code":"19","display":"Customer"},{"system":"http://terminology.hl7.org/CodeSystem/object-role","code":"20","display":"Job"},{"system":"http://terminology.hl7.org/CodeSystem/object-role","code":"21","display":"Job Stream"},{"system":"http://terminology.hl7.org/CodeSystem/object-role","code":"22","display":"Table"},{"system":"http://terminology.hl7.org/CodeSystem/object-role","code":"23","display":"Routing Criteria"},{"system":"http://terminology.hl7.org/CodeSystem/object-role","code":"24","display":"Query"}]}}