{"resourceType":"ValueSet","id":"v3-ActSite","meta":{"lastUpdated":"2018-04-01T00:00:00.000+10:00","profile":["http://hl7.org/fhir/StructureDefinition/shareablevalueset"]},"text":{"status":"generated","div":"<div xmlns=\"http://www.w3.org/1999/xhtml\"><p>Release Date: 2018-04-01</p>\r\n<table class=\"grid\">\r\n <tr><td><b>Level</b></td><td><b>Code</b></td><td><b>Display</b></td><td><b>Definition</b></td></tr>\r\n <tr><td>1</td><td><span style=\"color: grey\"><i>(_HumanActSite)</i></span> <b><i>Abstract</i></b></td><td><a name=\"v3-ActSite-_HumanActSite\"> </a></td><td>\n                        An anatomical location on a human which can be the focus of an act.<br/>\r\n\n                     </td></tr>\r\n <tr><td>2</td><td>  <span style=\"color: grey\"><i>(_HumanSubstanceAdministrationSite)</i></span> <b><i>Abstract</i></b></td><td><a name=\"v3-ActSite-_HumanSubstanceAdministrationSite\"> </a></td><td>\n                        The set of body locations to or through which a drug product may be administered.<br/>\r\n\n                     </td></tr>\r\n <tr><td>3</td><td>    BE<a name=\"v3-ActSite-BE\"> </a></td><td>bilateral ears</td><td/></tr>\r\n <tr><td>3</td><td>    BN<a name=\"v3-ActSite-BN\"> </a></td><td>bilateral nares</td><td/></tr>\r\n <tr><td>3</td><td>    BU<a name=\"v3-ActSite-BU\"> </a></td><td>buttock</td><td/></tr>\r\n <tr><td>3</td><td>    LA<a name=\"v3-ActSite-LA\"> </a></td><td>left arm</td><td/></tr>\r\n <tr><td>3</td><td>    LAC<a name=\"v3-ActSite-LAC\"> </a></td><td>left anterior chest</td><td/></tr>\r\n <tr><td>3</td><td>    LACF<a name=\"v3-ActSite-LACF\"> </a></td><td>left antecubital fossa</td><td/></tr>\r\n <tr><td>3</td><td>    LD<a name=\"v3-ActSite-LD\"> </a></td><td>left deltoid</td><td/></tr>\r\n <tr><td>3</td><td>    LE<a name=\"v3-ActSite-LE\"> </a></td><td>left ear</td><td/></tr>\r\n <tr><td>3</td><td>    LEJ<a name=\"v3-ActSite-LEJ\"> </a></td><td>left external jugular</td><td/></tr>\r\n <tr><td>3</td><td>    LF<a name=\"v3-ActSite-LF\"> </a></td><td>left foot</td><td/></tr>\r\n <tr><td>3</td><td>    LG<a name=\"v3-ActSite-LG\"> </a></td><td>left gluteus medius</td><td/></tr>\r\n <tr><td>3</td><td>    LH<a name=\"v3-ActSite-LH\"> </a></td><td>left hand</td><td/></tr>\r\n <tr><td>3</td><td>    LIJ<a name=\"v3-ActSite-LIJ\"> </a></td><td>left internal jugular</td><td/></tr>\r\n <tr><td>3</td><td>    LLAQ<a name=\"v3-ActSite-LLAQ\"> </a></td><td>left lower abd quadrant</td><td/></tr>\r\n <tr><td>3</td><td>    LLFA<a name=\"v3-ActSite-LLFA\"> </a></td><td>left lower forearm</td><td/></tr>\r\n <tr><td>3</td><td>    LMFA<a name=\"v3-ActSite-LMFA\"> </a></td><td>left mid forearm</td><td/></tr>\r\n <tr><td>3</td><td>    LN<a name=\"v3-ActSite-LN\"> </a></td><td>left naris</td><td/></tr>\r\n <tr><td>3</td><td>    LPC<a name=\"v3-ActSite-LPC\"> </a></td><td>left posterior chest</td><td/></tr>\r\n <tr><td>3</td><td>    LSC<a name=\"v3-ActSite-LSC\"> </a></td><td>left subclavian</td><td/></tr>\r\n <tr><td>3</td><td>    LT<a name=\"v3-ActSite-LT\"> </a></td><td>left thigh</td><td/></tr>\r\n <tr><td>3</td><td>    LUA<a name=\"v3-ActSite-LUA\"> </a></td><td>left upper arm</td><td/></tr>\r\n <tr><td>3</td><td>    LUAQ<a name=\"v3-ActSite-LUAQ\"> </a></td><td>left upper abd quadrant</td><td/></tr>\r\n <tr><td>3</td><td>    LUFA<a name=\"v3-ActSite-LUFA\"> </a></td><td>left upper forearm</td><td/></tr>\r\n <tr><td>3</td><td>    LVG<a name=\"v3-ActSite-LVG\"> </a></td><td>left ventragluteal</td><td/></tr>\r\n <tr><td>3</td><td>    LVL<a name=\"v3-ActSite-LVL\"> </a></td><td>left vastus lateralis</td><td/></tr>\r\n <tr><td>3</td><td>    OD<a name=\"v3-ActSite-OD\"> </a></td><td>right eye</td><td/></tr>\r\n <tr><td>3</td><td>    OS<a name=\"v3-ActSite-OS\"> </a></td><td>left eye</td><td/></tr>\r\n <tr><td>3</td><td>    OU<a name=\"v3-ActSite-OU\"> </a></td><td>bilateral eyes</td><td/></tr>\r\n <tr><td>3</td><td>    PA<a name=\"v3-ActSite-PA\"> </a></td><td>perianal</td><td/></tr>\r\n <tr><td>3</td><td>    PERIN<a name=\"v3-ActSite-PERIN\"> </a></td><td>perineal</td><td/></tr>\r\n <tr><td>3</td><td>    RA<a name=\"v3-ActSite-RA\"> </a></td><td>right arm</td><td/></tr>\r\n <tr><td>3</td><td>    RAC<a name=\"v3-ActSite-RAC\"> </a></td><td>right anterior chest</td><td/></tr>\r\n <tr><td>3</td><td>    RACF<a name=\"v3-ActSite-RACF\"> </a></td><td>right antecubital fossa</td><td/></tr>\r\n <tr><td>3</td><td>    RD<a name=\"v3-ActSite-RD\"> </a></td><td>right deltoid</td><td/></tr>\r\n <tr><td>3</td><td>    RE<a name=\"v3-ActSite-RE\"> </a></td><td>right ear</td><td/></tr>\r\n <tr><td>3</td><td>    REJ<a name=\"v3-ActSite-REJ\"> </a></td><td>right external jugular</td><td/></tr>\r\n <tr><td>3</td><td>    RF<a name=\"v3-ActSite-RF\"> </a></td><td>right foot</td><td/></tr>\r\n <tr><td>3</td><td>    RG<a name=\"v3-ActSite-RG\"> </a></td><td>right gluteus medius</td><td/></tr>\r\n <tr><td>3</td><td>    RH<a name=\"v3-ActSite-RH\"> </a></td><td>right hand</td><td/></tr>\r\n <tr><td>3</td><td>    RIJ<a name=\"v3-ActSite-RIJ\"> </a></td><td>right internal jugular</td><td/></tr>\r\n <tr><td>3</td><td>    RLAQ<a name=\"v3-ActSite-RLAQ\"> </a></td><td>right lower abd quadrant</td><td/></tr>\r\n <tr><td>3</td><td>    RLFA<a name=\"v3-ActSite-RLFA\"> </a></td><td>right lower forearm</td><td/></tr>\r\n <tr><td>3</td><td>    RMFA<a name=\"v3-ActSite-RMFA\"> </a></td><td>right mid forearm</td><td/></tr>\r\n <tr><td>3</td><td>    RN<a name=\"v3-ActSite-RN\"> </a></td><td>right naris</td><td/></tr>\r\n <tr><td>3</td><td>    RPC<a name=\"v3-ActSite-RPC\"> </a></td><td>right posterior chest</td><td/></tr>\r\n <tr><td>3</td><td>    RSC<a name=\"v3-ActSite-RSC\"> </a></td><td>right subclavian</td><td/></tr>\r\n <tr><td>3</td><td>    RT<a name=\"v3-ActSite-RT\"> </a></td><td>right thigh</td><td/></tr>\r\n <tr><td>3</td><td>    RUA<a name=\"v3-ActSite-RUA\"> </a></td><td>right upper arm</td><td/></tr>\r\n <tr><td>3</td><td>    RUAQ<a name=\"v3-ActSite-RUAQ\"> </a></td><td>right upper abd quadrant</td><td/></tr>\r\n <tr><td>3</td><td>    RUFA<a name=\"v3-ActSite-RUFA\"> </a></td><td>right upper forearm</td><td/></tr>\r\n <tr><td>3</td><td>    RVG<a name=\"v3-ActSite-RVG\"> </a></td><td>right ventragluteal</td><td/></tr>\r\n <tr><td>3</td><td>    RVL<a name=\"v3-ActSite-RVL\"> </a></td><td>right vastus lateralis</td><td/></tr>\r\n</table>\r\n</div>"},"extension":[{"url":"http://hl7.org/fhir/StructureDefinition/structuredefinition-ballot-status","valueString":"External"},{"url":"http://hl7.org/fhir/StructureDefinition/structuredefinition-fmm","valueInteger":0},{"url":"http://hl7.org/fhir/StructureDefinition/structuredefinition-wg","valueCode":"vocab"}],"url":"http://terminology.hl7.org/ValueSet/v3-ActSite","version":"2018-04-01","name":"v3 Code System ActSite","status":"active","experimental":false,"date":"2018-04-01","publisher":"HL7, Inc","contact":[{"telecom":[{"system":"url","value":"http://hl7.org"}]}],"description":" An anatomical location on an organism which can be the focus of an act.","immutable":true,"compose":{"include":[{"system":"http://terminology.hl7.org/CodeSystem/v3-ActSite"}]},"expansion":{"identifier":"urn:uuid:08d39fcc-8206-4a38-a040-a8bc88ee498a","timestamp":"2018-07-26T10:03:28+10:00","total":54,"parameter":[{"name":"excludeNested","valueBoolean":false},{"name":"includeDesignations","valueBoolean":true},{"name":"version","valueUri":"http://terminology.hl7.org/CodeSystem/v3-ActSite|2018-04-01"}],"contains":[{"system":"http://terminology.hl7.org/CodeSystem/v3-ActSite","abstract":true,"code":"_HumanActSite","display":"HumanActSite","contains":[{"system":"http://terminology.hl7.org/CodeSystem/v3-ActSite","abstract":true,"code":"_HumanSubstanceAdministrationSite","display":"HumanSubstanceAdministrationSite","contains":[{"system":"http://terminology.hl7.org/CodeSystem/v3-ActSite","code":"BE","display":"bilateral ears"},{"system":"http://terminology.hl7.org/CodeSystem/v3-ActSite","code":"BN","display":"bilateral nares"},{"system":"http://terminology.hl7.org/CodeSystem/v3-ActSite","code":"BU","display":"buttock"},{"system":"http://terminology.hl7.org/CodeSystem/v3-ActSite","code":"LA","display":"left arm"},{"system":"http://terminology.hl7.org/CodeSystem/v3-ActSite","code":"LAC","display":"left anterior chest"},{"system":"http://terminology.hl7.org/CodeSystem/v3-ActSite","code":"LACF","display":"left antecubital fossa"},{"system":"http://terminology.hl7.org/CodeSystem/v3-ActSite","code":"LD","display":"left deltoid"},{"system":"http://terminology.hl7.org/CodeSystem/v3-ActSite","code":"LE","display":"left ear"},{"system":"http://terminology.hl7.org/CodeSystem/v3-ActSite","code":"LEJ","display":"left external jugular"},{"system":"http://terminology.hl7.org/CodeSystem/v3-ActSite","code":"LF","display":"left foot"},{"system":"http://terminology.hl7.org/CodeSystem/v3-ActSite","code":"LG","display":"left gluteus medius"},{"system":"http://terminology.hl7.org/CodeSystem/v3-ActSite","code":"LH","display":"left hand"},{"system":"http://terminology.hl7.org/CodeSystem/v3-ActSite","code":"LIJ","display":"left internal jugular"},{"system":"http://terminology.hl7.org/CodeSystem/v3-ActSite","code":"LLAQ","display":"left lower abd quadrant"},{"system":"http://terminology.hl7.org/CodeSystem/v3-ActSite","code":"LLFA","display":"left lower forearm"},{"system":"http://terminology.hl7.org/CodeSystem/v3-ActSite","code":"LMFA","display":"left mid forearm"},{"system":"http://terminology.hl7.org/CodeSystem/v3-ActSite","code":"LN","display":"left naris"},{"system":"http://terminology.hl7.org/CodeSystem/v3-ActSite","code":"LPC","display":"left posterior chest"},{"system":"http://terminology.hl7.org/CodeSystem/v3-ActSite","code":"LSC","display":"left subclavian"},{"system":"http://terminology.hl7.org/CodeSystem/v3-ActSite","code":"LT","display":"left thigh"},{"system":"http://terminology.hl7.org/CodeSystem/v3-ActSite","code":"LUA","display":"left upper arm"},{"system":"http://terminology.hl7.org/CodeSystem/v3-ActSite","code":"LUAQ","display":"left upper abd quadrant"},{"system":"http://terminology.hl7.org/CodeSystem/v3-ActSite","code":"LUFA","display":"left upper forearm"},{"system":"http://terminology.hl7.org/CodeSystem/v3-ActSite","code":"LVG","display":"left ventragluteal"},{"system":"http://terminology.hl7.org/CodeSystem/v3-ActSite","code":"LVL","display":"left vastus lateralis"},{"system":"http://terminology.hl7.org/CodeSystem/v3-ActSite","code":"OD","display":"right eye"},{"system":"http://terminology.hl7.org/CodeSystem/v3-ActSite","code":"OS","display":"left eye"},{"system":"http://terminology.hl7.org/CodeSystem/v3-ActSite","code":"OU","display":"bilateral eyes"},{"system":"http://terminology.hl7.org/CodeSystem/v3-ActSite","code":"PA","display":"perianal"},{"system":"http://terminology.hl7.org/CodeSystem/v3-ActSite","code":"PERIN","display":"perineal"},{"system":"http://terminology.hl7.org/CodeSystem/v3-ActSite","code":"RA","display":"right arm"},{"system":"http://terminology.hl7.org/CodeSystem/v3-ActSite","code":"RAC","display":"right anterior chest"},{"system":"http://terminology.hl7.org/CodeSystem/v3-ActSite","code":"RACF","display":"right antecubital fossa"},{"system":"http://terminology.hl7.org/CodeSystem/v3-ActSite","code":"RD","display":"right deltoid"},{"system":"http://terminology.hl7.org/CodeSystem/v3-ActSite","code":"RE","display":"right ear"},{"system":"http://terminology.hl7.org/CodeSystem/v3-ActSite","code":"REJ","display":"right external jugular"},{"system":"http://terminology.hl7.org/CodeSystem/v3-ActSite","code":"RF","display":"right foot"},{"system":"http://terminology.hl7.org/CodeSystem/v3-ActSite","code":"RG","display":"right gluteus medius"},{"system":"http://terminology.hl7.org/CodeSystem/v3-ActSite","code":"RH","display":"right hand"},{"system":"http://terminology.hl7.org/CodeSystem/v3-ActSite","code":"RIJ","display":"right internal jugular"},{"system":"http://terminology.hl7.org/CodeSystem/v3-ActSite","code":"RLAQ","display":"right lower abd quadrant"},{"system":"http://terminology.hl7.org/CodeSystem/v3-ActSite","code":"RLFA","display":"right lower forearm"},{"system":"http://terminology.hl7.org/CodeSystem/v3-ActSite","code":"RMFA","display":"right mid forearm"},{"system":"http://terminology.hl7.org/CodeSystem/v3-ActSite","code":"RN","display":"right naris"},{"system":"http://terminology.hl7.org/CodeSystem/v3-ActSite","code":"RPC","display":"right posterior chest"},{"system":"http://terminology.hl7.org/CodeSystem/v3-ActSite","code":"RSC","display":"right subclavian"},{"system":"http://terminology.hl7.org/CodeSystem/v3-ActSite","code":"RT","display":"right thigh"},{"system":"http://terminology.hl7.org/CodeSystem/v3-ActSite","code":"RUA","display":"right upper arm"},{"system":"http://terminology.hl7.org/CodeSystem/v3-ActSite","code":"RUAQ","display":"right upper abd quadrant"},{"system":"http://terminology.hl7.org/CodeSystem/v3-ActSite","code":"RUFA","display":"right upper forearm"},{"system":"http://terminology.hl7.org/CodeSystem/v3-ActSite","code":"RVG","display":"right ventragluteal"},{"system":"http://terminology.hl7.org/CodeSystem/v3-ActSite","code":"RVL","display":"right vastus lateralis"}]}]}]}}