{"resourceType":"ValueSet","url":"http://hl7.org/fhir/ValueSet/nehta-pathology-test-result-status-va","version":"1.4.0","name":"PathologyTestResultStatusValues","status":"draft","experimental":false,"publisher":"HL7 (FHIR Project)","contact":[{"telecom":[{"system":"other","value":"http://hl7.org/fhir"},{"system":"email","value":"fhir@lists.hl7.org"}]}],"date":"2016-06-17T17:31:04+10:00","description":"Set of values for the pathology test result status.","compose":{"include":[{"system":"http://hl7.org/fhir/pathology-test-result-status-va"}]},"expansion":{"identifier":"urn:uuid:e01327b1-14e4-4d66-9abc-bcbc7735288a","timestamp":"2016-06-17T17:40:43+10:00","parameter":[{"name":"version","valueUri":"http://hl7.org/fhir/pathology-test-result-status-va?version=1.4.0"}],"contains":[{"system":"http://hl7.org/fhir/pathology-test-result-status-va","code":"1","display":"Registered"},{"system":"http://hl7.org/fhir/pathology-test-result-status-va","code":"2","display":"Interim"},{"system":"http://hl7.org/fhir/pathology-test-result-status-va","code":"3","display":"Final"},{"system":"http://hl7.org/fhir/pathology-test-result-status-va","code":"4","display":"Amended"},{"system":"http://hl7.org/fhir/pathology-test-result-status-va","code":"5","display":"Cancelled/Aborted"}]}}