{"resourceType":"ValueSet","id":"action-grouping-behavior","meta":{"lastUpdated":"2016-11-16T09:49:41.109+01:00","profile":["http://hl7.org/fhir/StructureDefinition/valueset-shareable-definition"]},"text":{"status":"generated","div":"<div xmlns=\"http://www.w3.org/1999/xhtml\"><h2>PlanActionGroupingBehavior</h2><div><p>Defines organization behavior of a group</p>\n</div><p>This value set includes codes from the following code systems:</p><ul><li>Include all codes defined in <a href=\"codesystem-action-grouping-behavior.html\">http://hl7.org/fhir/action-grouping-behavior</a></li></ul></div>"},"url":"http://hl7.org/fhir/ValueSet/action-grouping-behavior","identifier":[{"system":"urn:ietf:rfc:3986","value":"urn:oid:2.16.840.1.113883.4.642.2.988"}],"version":"1.7.0","name":"PlanActionGroupingBehavior","status":"draft","experimental":false,"publisher":"HL7 (FHIR Project)","contact":[{"telecom":[{"system":"other","value":"http://hl7.org/fhir"},{"system":"email","value":"fhir@lists.hl7.org"}]}],"date":"2016-11-16T09:49:41+01:00","description":"Defines organization behavior of a group","immutable":true,"compose":{"include":[{"system":"http://hl7.org/fhir/action-grouping-behavior"}]},"expansion":{"identifier":"urn:uuid:b7707a71-4ae3-4f73-bef6-3c4a70853f5b","timestamp":"2016-11-16T09:53:47+01:00","parameter":[{"name":"version","valueUri":"http://hl7.org/fhir/action-grouping-behavior?version=1.7.0"}],"contains":[{"system":"http://hl7.org/fhir/action-grouping-behavior","code":"visual-group","display":"Visual Group"},{"system":"http://hl7.org/fhir/action-grouping-behavior","code":"logical-group","display":"Logical Group"},{"system":"http://hl7.org/fhir/action-grouping-behavior","code":"sentence-group","display":"Sentence Group"}]}}